elrahpy/__init__.py
elrahpy/cryptokit/__init__.py
elrahpy/cryptokit/cesar.py
elrahpy/datekit/__init__.py
elrahpy/datekit/clock.py
elrahpy/fileskit/__init__.py
elrahpy/fileskit/filestools.py
elrahpy/intkit/__init__.py
elrahpy/intkit/math_primes.py
elrahpy/intkit/math_utils.py
elrahpy/intkit/t.py
elrahpy/strkit/__init__.py
elrahpy/strkit/charscraft.py
elrahpy/strkit/sequencescraft.py
elrahpy/turtlekit/__init__.py
elrahpy/turtlekit/geometric_shape.py
elrahpy/turtlekit/particular_shape.py
elrahpy/typeskit/__init__.py
elrahpy/typeskit/landmark.py
tests/__init__.py
tests/cryptokit/__init__.py
tests/cryptokit/test_cesar.py
tests/datekit/__init__.py
tests/datekit/test_clock.py
tests/fileskit/__init__.py
tests/fileskit/test_filestools.py
tests/intkit/__init__.py
tests/intkit/test_math_primes.py
tests/intkit/test_math_utils.py
tests/strkit/__init__.py
tests/strkit/test_charcraft.py
tests/strkit/test_sequencescraft.py
tests/typeskit/__init__.py
tests/typeskit/test_landmark.py
elrahpy-0.1.7.dist-info/METADATA
elrahpy-0.1.7.dist-info/WHEEL
elrahpy-0.1.7.dist-info/top_level.txt
elrahpy-0.1.7.dist-info/RECORD
