Metadata-Version: 2.4
Name: elrahpy
Version: 0.1.7
Summary: Package pour renforcer mes compétences, améliorer ma productivité et partager mon expertise avec la communauté 
Home-page: https://github.com/Harlequelrah/Library-ElrahPy
Author: Harlequelrah
Author-email: maximeatsoudegbovi@example.com
License: LGPL-3.0-only
Requires-Python: >=3.10
Requires-Dist: numpy>=1.18.0
Requires-Dist: python-dateutil
Requires-Dist: pytest
Requires-Dist: pytest-mock
Dynamic: author
Dynamic: author-email
Dynamic: description
Dynamic: description-content-type
Dynamic: home-page
Dynamic: license
Dynamic: requires-dist
Dynamic: requires-python
Dynamic: summary
